Full _adder/HA.sv
module HA(
    input logic a,b,
    output logic sum,carry
);

assign sum = a^b;
assign carry = a&b;

endmodule

Full _adder/FA.sv
module FA(
    input logic a,b,c,
    output logic sum,carry
);
logic w1,w2,w3;

HA ha1(
    .a(a), .b(b),
    .sum(w1), .carry(w2)
);

HA ha2(
    .a(w1), .b(c),
    .sum(sum), .carry(w3)
);

assign carry = w3|w2;

endmodule

Full _adder/FA_tb.sv
module FA_tb;
    
    logic a,b,c;
    logic sum,carry;

    FA DUT(.a(a), .b(b), .c(c), .sum(sum), .carry(carry));


    initial begin
        $dumpfile("wave.vcd");   // output file
        $dumpvars(0, FA_tb);  // dump all signals in TB scope
        $display("a b c | SUM  CARRY");
        $display("------|-----------");
        $monitor("%b %b %b | %b  %b",a,b,c,sum,carry);

        for(int i=0;i<8;i++)begin
            {a,b,c} = i;
            #10;
        end
        $finish;

    end

endmodule

Full _adder/wave.vcd
$date
	Tue Jun 16 13:22:28 2026
$end
$version
	Icarus Verilog
$end
$timescale
	1s
$end
$scope module FA_tb $end
$var wire 1 ! sum $end
$var wire 1 " carry $end
$var reg 1 # a $end
$var reg 1 $ b $end
$var reg 1 % c $end
$scope module DUT $end
$var wire 1 # a $end
$var wire 1 $ b $end
$var wire 1 % c $end
$var wire 1 " carry $end
$var wire 1 & w3 $end
$var wire 1 ' w2 $end
$var wire 1 ( w1 $end
$var wire 1 ! sum $end
$scope module ha1 $end
$var wire 1 # a $end
$var wire 1 $ b $end
$var wire 1 ' carry $end
$var wire 1 ( sum $end
$upscope $end
$scope module ha2 $end
$var wire 1 ( a $end
$var wire 1 % b $end
$var wire 1 & carry $end
$var wire 1 ! sum $end
$upscope $end
$upscope $end
$scope begin $ivl_for_loop0 $end
$var integer 32 ) i [31:0] $end
$upscope $end
$upscope $end
$enddefinitions $end
$comment Show the parameter values. $end
$dumpall
$end
#0
$dumpvars
b0 )
0(
0'
0&
0%
0$
0#
0"
0!
$end
#10
1!
1%
b1 )
#20
1(
1!
1$
0%
b10 )
#30
1"
0!
1&
1%
b11 )
#40
0"
1!
0&
1#
0$
0%
b100 )
#50
1"
0!
1&
1%
b101 )
#60
0(
1'
0!
0&
1$
0%
b110 )
#70
1!
1%
b111 )
#80
b1000 )
