ALU/ALU.sv
module ALU (
    input logic [7:0] a,b,
    input logic [3:0] cmd,
    input logic oe,
    output logic [15:0] dout
);

parameter ADD = 4'b0000,
          INC = 4'b0001,
          SUB = 4'b0010,
          DEC = 4'b0011,
          MUL = 4'b0100,
          DIV = 4'b0101,
          RSH = 4'b0110,
          LSH = 4'b0111,
          AND = 4'b1000,
          OR  = 4'b1001,
          INV  = 4'b1010,
          NAND = 4'b1011,
          NOR  = 4'b1100,
          XOR  = 4'b1101,
          XNOR = 4'b1110,
          BUF  = 4'b1111;

logic [15:0] result;

always_comb begin
    case (cmd)
    ADD: result = a+b;
    INC: result = a+1;
    SUB: result = a-b;
    DEC: result = a-1;
    MUL:  result = a * b;
    DIV:  result = a / b;
    RSH:  result = a >> 1;
    LSH:  result = a << 1;
    AND:  result = a & b;
    OR:   result = a | b;
    INV:  result = ~a;
    NAND: result = ~(a & b);
    NOR:  result = ~(a | b);
    XOR:  result = a ^ b;
    XNOR: result = ~(a ^ b);
    BUF:  result = a;
    default: result = 16'b0;
    endcase
    
end

    assign dout = oe ? result:16'bz;

    
endmodule

ALU/ALU_tb.sv
module ALU_tb;
    logic [7:0] a,b;
    logic [3:0] cmd;
    logic oe;
    logic [15:0] dout;

    ALU DUT(.a(a), .b(b), .cmd(cmd), .oe(oe), .dout(dout));

    localparam ADD=4'b0000, INC=4'b0001, SUB=4'b0010, DEC=4'b0011,
               MUL=4'b0100, DIV=4'b0101, RSH=4'b0110, LSH=4'b0111,
               AND=4'b1000, OR=4'b1001,  INV=4'b1010, NAND=4'b1011,
               NOR=4'b1100, XOR=4'b1101, XNOR=4'b1110, BUF=4'b1111;

    task test(input [7:0] ta,tb, input [3:0] tcmd, input string op_name);
        a = ta; b = tb; cmd = tcmd; oe = 1;
        #10;
        $display("%-20s | a=%0d b=%0d | dout=%0d", op_name, a, b, dout);//left align and 20 char wide padding
    endtask

    initial begin
        $dumpfile("wave.vcd");
        $dumpvars(0,ALU_tb);

        $display("%-20s | %-14s | dout", "Operation", "Inputs");
        $display("----------------------------------------------------");

        a = 8'd10; b = 8'd5;

        test(a,b,  ADD,  "Add");
        test(a, b, INC,  "Increment a");
        test(a, b, SUB,  "Subtract");
        test(a, b, DEC,  "Decrement a");
        test(a, b, MUL,  "Multiply");
        test(a, b, DIV,  "Divide");
        test(a, b, RSH,  "Shift right");
        test(a, b, LSH,  "Shift left");
        test(a, b, AND,  "AND");
        test(a, b, OR,   "OR");
        test(a, b, INV,  "Invert a");
        test(a, b, NAND, "NAND");
        test(a, b, NOR,  "NOR");
        test(a, b, XOR,  "XOR");
        test(a, b, XNOR, "XNOR");
        test(a, b, BUF,  "Buffer a");

        $finish;
    end


endmodule

ALU/wave.vcd
$date
	Tue Jun 16 14:53:52 2026
$end
$version
	Icarus Verilog
$end
$timescale
	1s
$end
$scope module ALU_tb $end
$var wire 16 ! dout [15:0] $end
$var parameter 4 " ADD $end
$var parameter 4 # AND $end
$var parameter 4 $ BUF $end
$var parameter 4 % DEC $end
$var parameter 4 & DIV $end
$var parameter 4 ' INC $end
$var parameter 4 ( INV $end
$var parameter 4 ) LSH $end
$var parameter 4 * MUL $end
$var parameter 4 + NAND $end
$var parameter 4 , NOR $end
$var parameter 4 - OR $end
$var parameter 4 . RSH $end
$var parameter 4 / SUB $end
$var parameter 4 0 XNOR $end
$var parameter 4 1 XOR $end
$var reg 8 2 a [7:0] $end
$var reg 8 3 b [7:0] $end
$var reg 4 4 cmd [3:0] $end
$var reg 1 5 oe $end
$scope module DUT $end
$var wire 8 6 a [7:0] $end
$var wire 8 7 b [7:0] $end
$var wire 4 8 cmd [3:0] $end
$var wire 1 5 oe $end
$var wire 16 9 dout [15:0] $end
$var parameter 4 : ADD $end
$var parameter 4 ; AND $end
$var parameter 4 < BUF $end
$var parameter 4 = DEC $end
$var parameter 4 > DIV $end
$var parameter 4 ? INC $end
$var parameter 4 @ INV $end
$var parameter 4 A LSH $end
$var parameter 4 B MUL $end
$var parameter 4 C NAND $end
$var parameter 4 D NOR $end
$var parameter 4 E OR $end
$var parameter 4 F RSH $end
$var parameter 4 G SUB $end
$var parameter 4 H XNOR $end
$var parameter 4 I XOR $end
$var reg 16 J result [15:0] $end
$upscope $end
$scope task test $end
$var reg 8 K ta [7:0] $end
$var reg 8 L tb [7:0] $end
$var reg 4 M tcmd [3:0] $end
$upscope $end
$upscope $end
$enddefinitions $end
$comment Show the parameter values. $end
$dumpall
b1101 I
b1110 H
b10 G
b110 F
b1001 E
b1100 D
b1011 C
b100 B
b111 A
b1010 @
b1 ?
b101 >
b11 =
b1111 <
b1000 ;
b0 :
b1101 1
b1110 0
b10 /
b110 .
b1001 -
b1100 ,
b1011 +
b100 *
b111 )
b1010 (
b1 '
b101 &
b11 %
b1111 $
b1000 #
b0 "
$end
#0
$dumpvars
b0 M
b101 L
b1010 K
b1111 J
b1111 9
b0 8
b101 7
b1010 6
15
b0 4
b101 3
b1010 2
b1111 !
$end
#10
b1011 !
b1011 9
b1011 J
b1 4
b1 8
b1 M
#20
b101 !
b101 9
b101 J
b10 4
b10 8
b10 M
#30
b1001 !
b1001 9
b1001 J
b11 4
b11 8
b11 M
#40
b110010 !
b110010 9
b110010 J
b100 4
b100 8
b100 M
#50
b10 !
b10 9
b10 J
b101 4
b101 8
b101 M
#60
b101 !
b101 9
b101 J
b110 4
b110 8
b110 M
#70
b10100 !
b10100 9
b10100 J
b111 4
b111 8
b111 M
#80
b0 !
b0 9
b0 J
b1000 4
b1000 8
b1000 M
#90
b1111 !
b1111 9
b1111 J
b1001 4
b1001 8
b1001 M
#100
b1111111111110101 !
b1111111111110101 9
b1111111111110101 J
b1010 4
b1010 8
b1010 M
#110
b1111111111111111 !
b1111111111111111 9
b1111111111111111 J
b1011 4
b1011 8
b1011 M
#120
b1111111111110000 !
b1111111111110000 9
b1111111111110000 J
b1100 4
b1100 8
b1100 M
#130
b1111 !
b1111 9
b1111 J
b1101 4
b1101 8
b1101 M
#140
b1111111111110000 !
b1111111111110000 9
b1111111111110000 J
b1110 4
b1110 8
b1110 M
#150
b1010 !
b1010 9
b1010 J
b1111 4
b1111 8
b1111 M
